<annotation>
	<folder>candleleafs</folder>
	<filename>P5150099.JPG</filename>
	<path>C:\Users\Boss\OPTICUT\Image candle\candleleafs\P5150099.JPG</path>
	<source>
		<database>Unknown</database>
	</source>
	<size>
		<width>3072</width>
		<height>2304</height>
		<depth>3</depth>
	</size>
	<segmented>0</segmented>
	<object>
		<name>candleleafs</name>
		<pose>Unspecified</pose>
		<truncated>0</truncated>
		<difficult>0</difficult>
		<bndbox>
			<xmin>599</xmin>
			<ymin>729</ymin>
			<xmax>2282</xmax>
			<ymax>1279</ymax>
		</bndbox>
	</object>
</annotation>
